{
  "id": "game-prpr-1747737074427",
  "name": "Pro Protocol",
  "symbol": "PRPR",
  "description": "Pro Protocol - a volatile crypto token with great potential for trading",
  "chartData": [
    {
      "timestamp": 1747736954427,
      "marketCap": 6667.992136164777
    },
    {
      "timestamp": 1747736955427,
      "marketCap": 7184.226179964557
    },
    {
      "timestamp": 1747736956427,
      "marketCap": 7487.826043819397
    },
    {
      "timestamp": 1747736957427,
      "marketCap": 7106.645729483985
    },
    {
      "timestamp": 1747736958427,
      "marketCap": 8448.642101721
    },
    {
      "timestamp": 1747736959427,
      "marketCap": 8808.586187183939
    },
    {
      "timestamp": 1747736960427,
      "marketCap": 8228.304445797672
    },
    {
      "timestamp": 1747736961427,
      "marketCap": 8730.247657531892
    },
    {
      "timestamp": 1747736962427,
      "marketCap": 8922.829148436003
    },
    {
      "timestamp": 1747736963427,
      "marketCap": 9144.066793352147
    },
    {
      "timestamp": 1747736964427,
      "marketCap": 9919.948088597752
    },
    {
      "timestamp": 1747736965427,
      "marketCap": 10004.738793413377
    },
    {
      "timestamp": 1747736966427,
      "marketCap": 10185.983180081652
    },
    {
      "timestamp": 1747736967427,
      "marketCap": 11436.085742859055
    },
    {
      "timestamp": 1747736968427,
      "marketCap": 10698.442420264666
    },
    {
      "timestamp": 1747736969427,
      "marketCap": 12130.134000354345
    },
    {
      "timestamp": 1747736970427,
      "marketCap": 12503.923496236204
    },
    {
      "timestamp": 1747736971427,
      "marketCap": 13307.86016355393
    },
    {
      "timestamp": 1747736972427,
      "marketCap": 13747.516385809191
    },
    {
      "timestamp": 1747736973427,
      "marketCap": 14052.014315961707
    },
    {
      "timestamp": 1747736974427,
      "marketCap": 14203.478929394152
    },
    {
      "timestamp": 1747736975427,
      "marketCap": 15543.882154717532
    },
    {
      "timestamp": 1747736976427,
      "marketCap": 15651.353979986292
    },
    {
      "timestamp": 1747736977427,
      "marketCap": 15996.994001093784
    },
    {
      "timestamp": 1747736978427,
      "marketCap": 15653.61708880572
    },
    {
      "timestamp": 1747736979427,
      "marketCap": 16216.590155282964
    },
    {
      "timestamp": 1747736980427,
      "marketCap": 17296.977570127456
    },
    {
      "timestamp": 1747736981427,
      "marketCap": 16963.841871503664
    },
    {
      "timestamp": 1747736982427,
      "marketCap": 19317.26461714936
    },
    {
      "timestamp": 1747736983427,
      "marketCap": 19615.993231700355
    },
    {
      "timestamp": 1747736984427,
      "marketCap": 20142.481873058343
    },
    {
      "timestamp": 1747736985427,
      "marketCap": 20732.050700508124
    },
    {
      "timestamp": 1747736986427,
      "marketCap": 19655.178751529857
    },
    {
      "timestamp": 1747736987427,
      "marketCap": 22095.701801635143
    },
    {
      "timestamp": 1747736988427,
      "marketCap": 21300.306135877996
    },
    {
      "timestamp": 1747736989427,
      "marketCap": 21417.922781109373
    },
    {
      "timestamp": 1747736990427,
      "marketCap": 23531.70979884841
    },
    {
      "timestamp": 1747736991427,
      "marketCap": 24237.328712323135
    },
    {
      "timestamp": 1747736992427,
      "marketCap": 23766.461160509603
    },
    {
      "timestamp": 1747736993427,
      "marketCap": 25167.434707211156
    },
    {
      "timestamp": 1747736994427,
      "marketCap": 25909.795331120607
    },
    {
      "timestamp": 1747736995427,
      "marketCap": 25203.375472755535
    },
    {
      "timestamp": 1747736996427,
      "marketCap": 27323.565229935004
    },
    {
      "timestamp": 1747736997427,
      "marketCap": 28224.093537879893
    },
    {
      "timestamp": 1747736998427,
      "marketCap": 29254.668094708195
    },
    {
      "timestamp": 1747736999427,
      "marketCap": 29189.17158256241
    },
    {
      "timestamp": 1747737000427,
      "marketCap": 29207.837415195703
    },
    {
      "timestamp": 1747737001427,
      "marketCap": 31348.584223957445
    },
    {
      "timestamp": 1747737002427,
      "marketCap": 31456.23190795822
    },
    {
      "timestamp": 1747737003427,
      "marketCap": 32196.591841604462
    },
    {
      "timestamp": 1747737004427,
      "marketCap": 31875.680321643278
    },
    {
      "timestamp": 1747737005427,
      "marketCap": 33056.02869202552
    },
    {
      "timestamp": 1747737006427,
      "marketCap": 33415.55271382433
    },
    {
      "timestamp": 1747737007427,
      "marketCap": 34178.59142797321
    },
    {
      "timestamp": 1747737008427,
      "marketCap": 34533.56762126591
    },
    {
      "timestamp": 1747737009427,
      "marketCap": 37722.56864874985
    },
    {
      "timestamp": 1747737010427,
      "marketCap": 36828.23446610925
    },
    {
      "timestamp": 1747737011427,
      "marketCap": 38564.48746269289
    },
    {
      "timestamp": 1747737012427,
      "marketCap": 39374.48847790859
    },
    {
      "timestamp": 1747737013427,
      "marketCap": 39790.2011950228
    },
    {
      "timestamp": 1747737014427,
      "marketCap": 41155.831238650506
    },
    {
      "timestamp": 1747737015427,
      "marketCap": 40567.77117779236
    },
    {
      "timestamp": 1747737016427,
      "marketCap": 42519.769319274885
    },
    {
      "timestamp": 1747737017427,
      "marketCap": 40898.897220809245
    },
    {
      "timestamp": 1747737018427,
      "marketCap": 42992.84615937337
    },
    {
      "timestamp": 1747737019427,
      "marketCap": 45224.1768598397
    },
    {
      "timestamp": 1747737020427,
      "marketCap": 44262.73734952939
    },
    {
      "timestamp": 1747737021427,
      "marketCap": 45636.74092410151
    },
    {
      "timestamp": 1747737022427,
      "marketCap": 45299.86690275493
    },
    {
      "timestamp": 1747737023427,
      "marketCap": 47912.61759489239
    },
    {
      "timestamp": 1747737024427,
      "marketCap": 46667.38856788691
    },
    {
      "timestamp": 1747737025427,
      "marketCap": 48766.04614571224
    },
    {
      "timestamp": 1747737026427,
      "marketCap": 50267.9136283486
    },
    {
      "timestamp": 1747737027427,
      "marketCap": 50743.82920559766
    },
    {
      "timestamp": 1747737028427,
      "marketCap": 51358.18124884948
    },
    {
      "timestamp": 1747737029427,
      "marketCap": 52894.11881557228
    },
    {
      "timestamp": 1747737030427,
      "marketCap": 54354.13944405802
    },
    {
      "timestamp": 1747737031427,
      "marketCap": 53701.97593925623
    },
    {
      "timestamp": 1747737032427,
      "marketCap": 56412.56917938923
    },
    {
      "timestamp": 1747737033427,
      "marketCap": 57389.258144069005
    },
    {
      "timestamp": 1747737034427,
      "marketCap": 58069.885766421496
    },
    {
      "timestamp": 1747737035427,
      "marketCap": 58653.30175850558
    },
    {
      "timestamp": 1747737036427,
      "marketCap": 58790.761110798325
    },
    {
      "timestamp": 1747737037427,
      "marketCap": 57684.07489368629
    },
    {
      "timestamp": 1747737038427,
      "marketCap": 58490.3379724046
    },
    {
      "timestamp": 1747737039427,
      "marketCap": 61424.697149050444
    },
    {
      "timestamp": 1747737040427,
      "marketCap": 61185.72582752379
    },
    {
      "timestamp": 1747737041427,
      "marketCap": 61014.32089869331
    },
    {
      "timestamp": 1747737042427,
      "marketCap": 62492.916128314464
    },
    {
      "timestamp": 1747737043427,
      "marketCap": 63296.24542974671
    },
    {
      "timestamp": 1747737044427,
      "marketCap": 66085.16200151356
    },
    {
      "timestamp": 1747737045427,
      "marketCap": 65673.41258379543
    },
    {
      "timestamp": 1747737046427,
      "marketCap": 70833.37945147106
    },
    {
      "timestamp": 1747737047427,
      "marketCap": 73931.83728975775
    },
    {
      "timestamp": 1747737048427,
      "marketCap": 77418.1113370112
    },
    {
      "timestamp": 1747737049427,
      "marketCap": 83378.98656672938
    },
    {
      "timestamp": 1747737050427,
      "marketCap": 84664.17872497665
    },
    {
      "timestamp": 1747737051427,
      "marketCap": 91863.69944859356
    },
    {
      "timestamp": 1747737052427,
      "marketCap": 92534.07277994123
    },
    {
      "timestamp": 1747737053427,
      "marketCap": 101649.76011470877
    },
    {
      "timestamp": 1747737054427,
      "marketCap": 102203.04438499021
    },
    {
      "timestamp": 1747737055427,
      "marketCap": 111650.37588405744
    },
    {
      "timestamp": 1747737056427,
      "marketCap": 117829.42245087186
    },
    {
      "timestamp": 1747737057427,
      "marketCap": 117171.91254325627
    },
    {
      "timestamp": 1747737058427,
      "marketCap": 125954.0200154458
    },
    {
      "timestamp": 1747737059427,
      "marketCap": 136585.1129433918
    },
    {
      "timestamp": 1747737060427,
      "marketCap": 140159.98213190306
    },
    {
      "timestamp": 1747737061427,
      "marketCap": 143729.36802633962
    },
    {
      "timestamp": 1747737062427,
      "marketCap": 148531.70472764803
    },
    {
      "timestamp": 1747737063427,
      "marketCap": 163370.81804404245
    },
    {
      "timestamp": 1747737064427,
      "marketCap": 171900.61465805766
    },
    {
      "timestamp": 1747737065427,
      "marketCap": 175101.46489275957
    },
    {
      "timestamp": 1747737066427,
      "marketCap": 181973.35291249322
    },
    {
      "timestamp": 1747737067427,
      "marketCap": 188308.47723302292
    },
    {
      "timestamp": 1747737068427,
      "marketCap": 201822.3316240032
    },
    {
      "timestamp": 1747737069427,
      "marketCap": 211885.32309100952
    },
    {
      "timestamp": 1747737070427,
      "marketCap": 209325.1615995506
    },
    {
      "timestamp": 1747737071427,
      "marketCap": 218678.77803760927
    },
    {
      "timestamp": 1747737072427,
      "marketCap": 228729.96156447296
    },
    {
      "timestamp": 1747737073427,
      "marketCap": 245940.53675525833
    }
  ],
  "currentMarketCap": 245940.53675525833,
  "iconUrl": "data:image/svg+xml;base64,CiAgICA8c3ZnIHhtbG5zPSJodHRwOi8vd3d3LnczLm9yZy8yMDAwL3N2ZyIgdmlld0JveD0iMCAwIDEwMCAxMDAiIHdpZHRoPSIxMDAlIiBoZWlnaHQ9IjEwMCUiPgogICAgICA8Y2lyY2xlIGN4PSI1MCIgY3k9IjUwIiByPSI1MCIgZmlsbD0iIzFFOTBGRiIgLz4KICAgICAgPHRleHQgeD0iNTAiIHk9IjUwIiBmb250LWZhbWlseT0iQXJpYWwsIHNhbnMtc2VyaWYiIGZvbnQtc2l6ZT0iNDAiIGZvbnQtd2VpZ2h0PSJib2xkIiBmaWxsPSJ3aGl0ZSIgdGV4dC1hbmNob3I9Im1pZGRsZSIgZG9taW5hbnQtYmFzZWxpbmU9ImNlbnRyYWwiPlA8L3RleHQ+CiAgICA8L3N2Zz4KICA=",
  "strategy": "uptrend_with_dumps"
}